[
  {
    "agent_ref": {
      "name": "marketplace_agent"
    },
    "agent_metrics": {
      "mean/reward": 0.6507,
      "mean/id": 2.0,
      "mean/input_tokens": 2026250.0,
      "mean/output_tokens": 4453.4,
      "mean/total_tokens": 2030703.4,
      "mean/cost": 0.010369199999999999,
      "mean/is_byok": 0.0,
      "max/reward": 0.7615,
      "max/id": 4.0,
      "max/input_tokens": 2124335.0,
      "max/output_tokens": 4867.0,
      "max/total_tokens": 2128796.0,
      "max/cost": 0.010731,
      "max/is_byok": 0.0,
      "min/reward": 0.5584,
      "min/id": 0.0,
      "min/input_tokens": 1952828.0,
      "min/output_tokens": 3776.0,
      "min/total_tokens": 1956604.0,
      "min/cost": 0.009981,
      "min/is_byok": 0.0,
      "median/reward": 0.6142,
      "median/id": 2.0,
      "median/input_tokens": 2013138.0,
      "median/output_tokens": 4461.0,
      "median/total_tokens": 2017543.0,
      "median/cost": 0.010452,
      "median/is_byok": 0.0,
      "std/reward": 0.09579431089579381,
      "std/id": 1.5811388300841898,
      "std/input_tokens": 67359.06189593201,
      "std/output_tokens": 425.7690688624527,
      "std/total_tokens": 67549.859202666,
      "std/cost": 0.00031494713842167207,
      "std/is_byok": 0.0
    },
    "key_metrics": {
      "mean/reward": 0.6507,
      "mean/id": 2.0,
      "mean/input_tokens": 2026250.0,
      "mean/output_tokens": 4453.4,
      "mean/total_tokens": 2030703.4,
      "mean/cost": 0.010369199999999999,
      "mean/is_byok": 0.0
    },
    "group_level_metrics": [
      {
        "_ng_task_index": 0,
        "mean/reward": 0.6142,
        "mean/id": 0.0,
        "mean/input_tokens": 2058546.0,
        "mean/output_tokens": 4867.0,
        "mean/total_tokens": 2063413.0,
        "mean/cost": 0.01011,
        "mean/is_byok": 0.0,
        "max/reward": 0.6142,
        "max/id": 0.0,
        "max/input_tokens": 2058546.0,
        "max/output_tokens": 4867.0,
        "max/total_tokens": 2063413.0,
        "max/cost": 0.01011,
        "max/is_byok": 0.0,
        "min/reward": 0.6142,
        "min/id": 0.0,
        "min/input_tokens": 2058546.0,
        "min/output_tokens": 4867.0,
        "min/total_tokens": 2063413.0,
        "min/cost": 0.01011,
        "min/is_byok": 0.0,
        "median/reward": 0.6142,
        "median/id": 0.0,
        "median/input_tokens": 2058546.0,
        "median/output_tokens": 4867.0,
        "median/total_tokens": 2063413.0,
        "median/cost": 0.01011,
        "median/is_byok": 0.0,
        "std/reward": 0.0,
        "std/id": 0.0,
        "std/input_tokens": 0.0,
        "std/output_tokens": 0.0,
        "std/total_tokens": 0.0,
        "std/cost": 0.0,
        "std/is_byok": 0.0,
        "sample": {
          "agent_ref": {
            "name": "agent"
          }
        },
        "num_rollouts": 1,
        "expected_num_rollouts": 1,
        "missing_num_rollouts": 0,
        "reward_profile_completion_pct": 100.0,
        "rollout_infos": [
          {
            "rollout_id": "0:0",
            "_ng_task_index": 0,
            "_ng_rollout_index": 0,
            "reward": 0.6142,
            "input_tokens": 2058546,
            "output_tokens": 4867,
            "total_tokens": 2063413,
            "cost": 0.01011,
            "is_byok": 0,
            "id": 0
          }
        ]
      },
      {
        "_ng_task_index": 1,
        "mean/reward": 0.5748,
        "mean/id": 1.0,
        "mean/input_tokens": 1952828.0,
        "mean/output_tokens": 3776.0,
        "mean/total_tokens": 1956604.0,
        "mean/cost": 0.009981,
        "mean/is_byok": 0.0,
        "max/reward": 0.5748,
        "max/id": 1.0,
        "max/input_tokens": 1952828.0,
        "max/output_tokens": 3776.0,
        "max/total_tokens": 1956604.0,
        "max/cost": 0.009981,
        "max/is_byok": 0.0,
        "min/reward": 0.5748,
        "min/id": 1.0,
        "min/input_tokens": 1952828.0,
        "min/output_tokens": 3776.0,
        "min/total_tokens": 1956604.0,
        "min/cost": 0.009981,
        "min/is_byok": 0.0,
        "median/reward": 0.5748,
        "median/id": 1.0,
        "median/input_tokens": 1952828.0,
        "median/output_tokens": 3776.0,
        "median/total_tokens": 1956604.0,
        "median/cost": 0.009981,
        "median/is_byok": 0.0,
        "std/reward": 0.0,
        "std/id": 0.0,
        "std/input_tokens": 0.0,
        "std/output_tokens": 0.0,
        "std/total_tokens": 0.0,
        "std/cost": 0.0,
        "std/is_byok": 0.0,
        "sample": {
          "agent_ref": {
            "name": "agent"
          }
        },
        "num_rollouts": 1,
        "expected_num_rollouts": 1,
        "missing_num_rollouts": 0,
        "reward_profile_completion_pct": 100.0,
        "rollout_infos": [
          {
            "rollout_id": "1:0",
            "_ng_task_index": 1,
            "_ng_rollout_index": 0,
            "reward": 0.5748,
            "input_tokens": 1952828,
            "output_tokens": 3776,
            "total_tokens": 1956604,
            "cost": 0.009981,
            "is_byok": 0,
            "id": 1
          }
        ]
      },
      {
        "_ng_task_index": 2,
        "mean/reward": 0.5584,
        "mean/id": 2.0,
        "mean/input_tokens": 2013138.0,
        "mean/output_tokens": 4405.0,
        "mean/total_tokens": 2017543.0,
        "mean/cost": 0.010452,
        "mean/is_byok": 0.0,
        "max/reward": 0.5584,
        "max/id": 2.0,
        "max/input_tokens": 2013138.0,
        "max/output_tokens": 4405.0,
        "max/total_tokens": 2017543.0,
        "max/cost": 0.010452,
        "max/is_byok": 0.0,
        "min/reward": 0.5584,
        "min/id": 2.0,
        "min/input_tokens": 2013138.0,
        "min/output_tokens": 4405.0,
        "min/total_tokens": 2017543.0,
        "min/cost": 0.010452,
        "min/is_byok": 0.0,
        "median/reward": 0.5584,
        "median/id": 2.0,
        "median/input_tokens": 2013138.0,
        "median/output_tokens": 4405.0,
        "median/total_tokens": 2017543.0,
        "median/cost": 0.010452,
        "median/is_byok": 0.0,
        "std/reward": 0.0,
        "std/id": 0.0,
        "std/input_tokens": 0.0,
        "std/output_tokens": 0.0,
        "std/total_tokens": 0.0,
        "std/cost": 0.0,
        "std/is_byok": 0.0,
        "sample": {
          "agent_ref": {
            "name": "agent"
          }
        },
        "num_rollouts": 1,
        "expected_num_rollouts": 1,
        "missing_num_rollouts": 0,
        "reward_profile_completion_pct": 100.0,
        "rollout_infos": [
          {
            "rollout_id": "2:0",
            "_ng_task_index": 2,
            "_ng_rollout_index": 0,
            "reward": 0.5584,
            "input_tokens": 2013138,
            "output_tokens": 4405,
            "total_tokens": 2017543,
            "cost": 0.010452,
            "is_byok": 0,
            "id": 2
          }
        ]
      },
      {
        "_ng_task_index": 3,
        "mean/reward": 0.7446,
        "mean/id": 3.0,
        "mean/input_tokens": 2124335.0,
        "mean/output_tokens": 4461.0,
        "mean/total_tokens": 2128796.0,
        "mean/cost": 0.010572,
        "mean/is_byok": 0.0,
        "max/reward": 0.7446,
        "max/id": 3.0,
        "max/input_tokens": 2124335.0,
        "max/output_tokens": 4461.0,
        "max/total_tokens": 2128796.0,
        "max/cost": 0.010572,
        "max/is_byok": 0.0,
        "min/reward": 0.7446,
        "min/id": 3.0,
        "min/input_tokens": 2124335.0,
        "min/output_tokens": 4461.0,
        "min/total_tokens": 2128796.0,
        "min/cost": 0.010572,
        "min/is_byok": 0.0,
        "median/reward": 0.7446,
        "median/id": 3.0,
        "median/input_tokens": 2124335.0,
        "median/output_tokens": 4461.0,
        "median/total_tokens": 2128796.0,
        "median/cost": 0.010572,
        "median/is_byok": 0.0,
        "std/reward": 0.0,
        "std/id": 0.0,
        "std/input_tokens": 0.0,
        "std/output_tokens": 0.0,
        "std/total_tokens": 0.0,
        "std/cost": 0.0,
        "std/is_byok": 0.0,
        "sample": {
          "agent_ref": {
            "name": "agent"
          }
        },
        "num_rollouts": 1,
        "expected_num_rollouts": 1,
        "missing_num_rollouts": 0,
        "reward_profile_completion_pct": 100.0,
        "rollout_infos": [
          {
            "rollout_id": "3:0",
            "_ng_task_index": 3,
            "_ng_rollout_index": 0,
            "reward": 0.7446,
            "input_tokens": 2124335,
            "output_tokens": 4461,
            "total_tokens": 2128796,
            "cost": 0.010572,
            "is_byok": 0,
            "id": 3
          }
        ]
      },
      {
        "_ng_task_index": 4,
        "mean/reward": 0.7615,
        "mean/id": 4.0,
        "mean/input_tokens": 1982403.0,
        "mean/output_tokens": 4758.0,
        "mean/total_tokens": 1987161.0,
        "mean/cost": 0.010731,
        "mean/is_byok": 0.0,
        "max/reward": 0.7615,
        "max/id": 4.0,
        "max/input_tokens": 1982403.0,
        "max/output_tokens": 4758.0,
        "max/total_tokens": 1987161.0,
        "max/cost": 0.010731,
        "max/is_byok": 0.0,
        "min/reward": 0.7615,
        "min/id": 4.0,
        "min/input_tokens": 1982403.0,
        "min/output_tokens": 4758.0,
        "min/total_tokens": 1987161.0,
        "min/cost": 0.010731,
        "min/is_byok": 0.0,
        "median/reward": 0.7615,
        "median/id": 4.0,
        "median/input_tokens": 1982403.0,
        "median/output_tokens": 4758.0,
        "median/total_tokens": 1987161.0,
        "median/cost": 0.010731,
        "median/is_byok": 0.0,
        "std/reward": 0.0,
        "std/id": 0.0,
        "std/input_tokens": 0.0,
        "std/output_tokens": 0.0,
        "std/total_tokens": 0.0,
        "std/cost": 0.0,
        "std/is_byok": 0.0,
        "sample": {
          "agent_ref": {
            "name": "agent"
          }
        },
        "num_rollouts": 1,
        "expected_num_rollouts": 1,
        "missing_num_rollouts": 0,
        "reward_profile_completion_pct": 100.0,
        "rollout_infos": [
          {
            "rollout_id": "4:0",
            "_ng_task_index": 4,
            "_ng_rollout_index": 0,
            "reward": 0.7615,
            "input_tokens": 1982403,
            "output_tokens": 4758,
            "total_tokens": 1987161,
            "cost": 0.010731,
            "is_byok": 0,
            "id": 4
          }
        ]
      }
    ]
  }
]