{
  "deals": [
    {
      "deal_id": "deal_001",
      "seller": "Luna",
      "buyer": "Finn",
      "item_id": "set_02_luna_bottoms_01",
      "item_name": "Skirt",
      "price": -1.0,
      "seller_floor": 26.0,
      "buyer_ceiling": 54.0,
      "turn": 30,
      "deal_type": "swap",
      "item_b_id": "set_02_finn_dresses_01",
      "item_b_name": "Red Dress",
      "item_b_floor": 34.0,
      "item_a_ceiling": 79.0
    },
    {
      "deal_id": "deal_002",
      "seller": "Iris",
      "buyer": "Sage",
      "item_id": "set_02_iris_outerwear_01",
      "item_name": "Blue Striped Sweater",
      "price": -1.0,
      "seller_floor": 59.0,
      "buyer_ceiling": 100.0,
      "turn": 44,
      "deal_type": "swap",
      "item_b_id": "set_02_sage_tops_01",
      "item_b_name": "White Top",
      "item_b_floor": 27.0,
      "item_a_ceiling": 39.0
    },
    {
      "deal_id": "deal_003",
      "seller": "Zoe",
      "buyer": "Mira",
      "item_id": "set_02_zoe_bottoms_01",
      "item_name": "And Plaid Pants",
      "price": -1.0,
      "seller_floor": 38.0,
      "buyer_ceiling": 52.0,
      "turn": 54,
      "deal_type": "swap",
      "item_b_id": "set_02_mira_dresses_01",
      "item_b_name": "Striped Dress",
      "item_b_floor": 31.0,
      "item_a_ceiling": 69.0
    }
  ],
  "fulfilled_want_ids": [
    "set_02_zoe_want_dresses",
    "set_02_finn_want_bottoms",
    "set_02_sage_want_outerwear",
    "set_02_mira_want_bottoms",
    "set_02_luna_want_dresses",
    "set_02_iris_want_tops"
  ]
}